.gitignore
.travis.yml
LICENSE.txt
MANIFEST.in
README.rst
requirements.txt
setup.py
tox.ini
WeatherAlerts.egg-info/PKG-INFO
WeatherAlerts.egg-info/SOURCES.txt
WeatherAlerts.egg-info/dependency_links.txt
WeatherAlerts.egg-info/requires.txt
WeatherAlerts.egg-info/top_level.txt
docs/Makefile
docs/about.rst
docs/changelog.rst
docs/conf.py
docs/index.rst
docs/module.rst
docs/nwsdata.rst
docs/use.rst
docs/webservice.rst
docs/_static/.gitignore
scripts/.gitignore
tests/__init__.py
tests/__init__.pyc
tests/test_cap.py
tests/test_cap.pyc
tests/test_feed.py
tests/test_feed.pyc
tests/test_geodb.py
tests/test_geodb.pyc
tests/test_weatheralerts.py
tests/test_weatheralerts.pyc
tests/__pycache__/__init__.cpython-35.pyc
tests/__pycache__/__init__.cpython-36.pyc
tests/__pycache__/test_cap.cpython-35.pyc
tests/__pycache__/test_cap.cpython-36.pyc
tests/__pycache__/test_feed.cpython-35.pyc
tests/__pycache__/test_feed.cpython-36.pyc
tests/__pycache__/test_geodb.cpython-35.pyc
tests/__pycache__/test_geodb.cpython-36.pyc
tests/__pycache__/test_weatheralerts.cpython-35.pyc
tests/__pycache__/test_weatheralerts.cpython-36.pyc
weatheralerts/__init__.py
weatheralerts/alert.py
weatheralerts/cap.py
weatheralerts/feed.py
weatheralerts/geo.py
weatheralerts/weather_alerts.py